{"data": [{"legendgroup": "1v1-stochastic", "line": {"color": "rgb(255,0,0)"}, "mode": "lines", "name": "1v1-stochastic", "showlegend": true, "visible": "legendonly", "x": [0, 1, 2, 3, 4, 5], "y": [0.0, 0.06254548064286031, -0.11050169306278716, -0.029308356556099563, -0.13119838526460476, 0.04434332718890793], "type": "scatter"}, {"fill": "toself", "fillcolor": "rgba(255,0,0,0.2)", "hoverinfo": "skip", "legendgroup": "1v1-stochastic", "line": {"color": "rgba(255,255,255,0)"}, "name": "sigma", "showlegend": false, "visible": "legendonly", "x": [0, 1, 2, 3, 4, 5, 5, 4, 3, 2, 1, 0], "y": [2.0, 2.0625454806428603, 1.8894983069372129, 1.9706916434439004, 1.8688016147353952, 2.0905466598267224, -2.0018600054489064, -2.1311983852646046, -2.0293083565560996, -2.1105016930627873, -1.9374545193571397, -2.0], "type": "scatter"}, {"legendgroup": "1v1-deterministic", "line": {"color": "rgb(128,0,0)"}, "mode": "lines", "name": "1v1-deterministic", "showlegend": true, "visible": "legendonly", "x": [0, 1, 2, 3, 4, 5], "y": [-0.09935244014321915, -0.061949810198505, -0.25068230563753224, -0.4110098143779861, -0.27544877716757243, -0.3415785592728936], "type": "scatter"}, {"fill": "toself", "fillcolor": "rgba(128,0,0,0.2)", "hoverinfo": "skip", "legendgroup": "1v1-deterministic", "line": {"color": "rgba(255,255,255,0)"}, "name": "sigma", "showlegend": false, "visible": "legendonly", "x": [0, 1, 2, 3, 4, 5, 5, 4, 3, 2, 1, 0], "y": [1.900647559856781, 1.938050189801495, 1.7493176943624678, 1.5889901856220139, 1.7245512228324276, 2.013176109801036, -2.696333228346823, -2.2754487771675724, -2.4110098143779863, -2.2506823056375325, -2.061949810198505, -2.0993524401432193], "type": "scatter"}, {"legendgroup": "2v2-stochastic", "line": {"color": "rgb(0,255,0)"}, "mode": "lines", "name": "2v2-stochastic", "showlegend": true, "visible": "legendonly", "x": [0, 1, 2, 3, 4, 5], "y": [0.0, 0.0, 0.0, 0.0, 0.0, 0.0], "type": "scatter"}, {"fill": "toself", "fillcolor": "rgba(0,255,0,0.2)", "hoverinfo": "skip", "legendgroup": "2v2-stochastic", "line": {"color": "rgba(255,255,255,0)"}, "name": "sigma", "showlegend": false, "visible": "legendonly", "x": [0, 1, 2, 3, 4, 5, 5, 4, 3, 2, 1, 0], "y": [2.0, 16.666666666666668, 16.666666666666668, 16.666666666666668, 16.666666666666668, 16.666666666666668, -16.666666666666668, -16.666666666666668, -16.666666666666668, -16.666666666666668, -16.666666666666668, -2.0], "type": "scatter"}, {"legendgroup": "2v2-deterministic", "line": {"color": "rgb(0,128,0)"}, "mode": "lines", "name": "2v2-deterministic", "showlegend": true, "visible": "legendonly", "x": [0, 1, 2, 3, 4, 5], "y": [0.0, 0.0, 0.0, 0.0, 0.0, 0.0], "type": "scatter"}, {"fill": "toself", "fillcolor": "rgba(0,128,0,0.2)", "hoverinfo": "skip", "legendgroup": "2v2-deterministic", "line": {"color": "rgba(255,255,255,0)"}, "name": "sigma", "showlegend": false, "visible": "legendonly", "x": [0, 1, 2, 3, 4, 5, 5, 4, 3, 2, 1, 0], "y": [2.0, 16.666666666666668, 16.666666666666668, 16.666666666666668, 16.666666666666668, 16.666666666666668, -16.666666666666668, -16.666666666666668, -16.666666666666668, -16.666666666666668, -16.666666666666668, -2.0], "type": "scatter"}, {"legendgroup": "3v3-stochastic", "line": {"color": "rgb(0,0,255)"}, "mode": "lines", "name": "3v3-stochastic", "showlegend": true, "visible": "legendonly", "x": [0, 1, 2, 3, 4, 5], "y": [0.0, 0.0, 0.0, 0.0, 0.0, 0.0], "type": "scatter"}, {"fill": "toself", "fillcolor": "rgba(0,0,255,0.2)", "hoverinfo": "skip", "legendgroup": "3v3-stochastic", "line": {"color": "rgba(255,255,255,0)"}, "name": "sigma", "showlegend": false, "visible": "legendonly", "x": [0, 1, 2, 3, 4, 5, 5, 4, 3, 2, 1, 0], "y": [2.0, 16.666666666666668, 16.666666666666668, 16.666666666666668, 16.666666666666668, 16.666666666666668, -16.666666666666668, -16.666666666666668, -16.666666666666668, -16.666666666666668, -16.666666666666668, -2.0], "type": "scatter"}, {"legendgroup": "3v3-deterministic", "line": {"color": "rgb(0,0,128)"}, "mode": "lines", "name": "3v3-deterministic", "showlegend": true, "visible": "legendonly", "x": [0, 1, 2, 3, 4, 5], "y": [0.0, 0.0, 0.0, 0.0, 0.0, 0.0], "type": "scatter"}, {"fill": "toself", "fillcolor": "rgba(0,0,128,0.2)", "hoverinfo": "skip", "legendgroup": "3v3-deterministic", "line": {"color": "rgba(255,255,255,0)"}, "name": "sigma", "showlegend": false, "visible": "legendonly", "x": [0, 1, 2, 3, 4, 5, 5, 4, 3, 2, 1, 0], "y": [2.0, 16.666666666666668, 16.666666666666668, 16.666666666666668, 16.666666666666668, 16.666666666666668, -16.666666666666668, -16.666666666666668, -16.666666666666668, -16.666666666666668, -16.666666666666668, -2.0], "type": "scatter"}, {"legendgroup": "mean-stochastic", "line": {"color": "rgb(85,85,85)"}, "mode": "lines", "name": "mean-stochastic", "showlegend": true, "x": [0, 1, 2, 3, 4, 5], "y": [0.0, 0.020848493547620105, -0.03683389768759572, -0.009769452185366519, -0.04373279508820158, 0.014781109062969318], "type": "scatter"}, {"fill": "toself", "fillcolor": "rgba(85,85,85,0.2)", "hoverinfo": "skip", "legendgroup": "mean-stochastic", "line": {"color": "rgba(255,255,255,0)"}, "name": "sigma", "showlegend": false, "x": [0, 1, 2, 3, 4, 5, 5, 4, 3, 2, 1, 0], "y": [2.0, 13.678026771600468, 13.620344380365253, 13.647408825867481, 13.613445482964647, 13.674240635145418, -13.64467841701948, -13.70091107314105, -13.666947730238215, -13.694012175740443, -13.636329784505229, -2.0], "type": "scatter"}, {"legendgroup": "mean-deterministic", "line": {"color": "rgb(42,42,42)"}, "mode": "lines", "name": "mean-deterministic", "showlegend": true, "x": [0, 1, 2, 3, 4, 5], "y": [-0.03311748004773972, -0.020649936732834998, -0.08356076854584407, -0.1370032714593287, -0.09181625905585747, -0.1138595197576312], "type": "scatter"}, {"fill": "toself", "fillcolor": "rgba(42,42,42,0.2)", "hoverinfo": "skip", "legendgroup": "mean-deterministic", "line": {"color": "rgba(255,255,255,0)"}, "name": "sigma", "showlegend": false, "x": [0, 1, 2, 3, 4, 5, 5, 4, 3, 2, 1, 0], "y": [1.9668825199522604, 13.636528341320012, 13.573617509507004, 13.52017500659352, 13.565362018996991, 13.562158725173667, -13.789877764688928, -13.748994537108706, -13.794181549512176, -13.740739046598692, -13.677828214785684, -2.0331174800477396], "type": "scatter"}], "layout": {"template": {"data": {"histogram2dcontour": [{"type": "histogram2dcontour", "colorbar": {"outlinewidth": 0, "ticks": ""}, "colorscale": [[0.0, "#0d0887"], [0.1111111111111111, "#46039f"], [0.2222222222222222, "#7201a8"], [0.3333333333333333, "#9c179e"], [0.4444444444444444, "#bd3786"], [0.5555555555555556, "#d8576b"], [0.6666666666666666, "#ed7953"], [0.7777777777777778, "#fb9f3a"], [0.8888888888888888, "#fdca26"], [1.0, "#f0f921"]]}], "choropleth": [{"type": "choropleth", "colorbar": {"outlinewidth": 0, "ticks": ""}}], "histogram2d": [{"type": "histogram2d", "colorbar": {"outlinewidth": 0, "ticks": ""}, "colorscale": [[0.0, "#0d0887"], [0.1111111111111111, "#46039f"], [0.2222222222222222, "#7201a8"], [0.3333333333333333, "#9c179e"], [0.4444444444444444, "#bd3786"], [0.5555555555555556, "#d8576b"], [0.6666666666666666, "#ed7953"], [0.7777777777777778, "#fb9f3a"], [0.8888888888888888, "#fdca26"], [1.0, "#f0f921"]]}], "heatmap": [{"type": "heatmap", "colorbar": {"outlinewidth": 0, "ticks": ""}, "colorscale": [[0.0, "#0d0887"], [0.1111111111111111, "#46039f"], [0.2222222222222222, "#7201a8"], [0.3333333333333333, "#9c179e"], [0.4444444444444444, "#bd3786"], [0.5555555555555556, "#d8576b"], [0.6666666666666666, "#ed7953"], [0.7777777777777778, "#fb9f3a"], [0.8888888888888888, "#fdca26"], [1.0, "#f0f921"]]}], "heatmapgl": [{"type": "heatmapgl", "colorbar": {"outlinewidth": 0, "ticks": ""}, "colorscale": [[0.0, "#0d0887"], [0.1111111111111111, "#46039f"], [0.2222222222222222, "#7201a8"], [0.3333333333333333, "#9c179e"], [0.4444444444444444, "#bd3786"], [0.5555555555555556, "#d8576b"], [0.6666666666666666, "#ed7953"], [0.7777777777777778, "#fb9f3a"], [0.8888888888888888, "#fdca26"], [1.0, "#f0f921"]]}], "contourcarpet": [{"type": "contourcarpet", "colorbar": {"outlinewidth": 0, "ticks": ""}}], "contour": [{"type": "contour", "colorbar": {"outlinewidth": 0, "ticks": ""}, "colorscale": [[0.0, "#0d0887"], [0.1111111111111111, "#46039f"], [0.2222222222222222, "#7201a8"], [0.3333333333333333, "#9c179e"], [0.4444444444444444, "#bd3786"], [0.5555555555555556, "#d8576b"], [0.6666666666666666, "#ed7953"], [0.7777777777777778, "#fb9f3a"], [0.8888888888888888, "#fdca26"], [1.0, "#f0f921"]]}], "surface": [{"type": "surface", "colorbar": {"outlinewidth": 0, "ticks": ""}, "colorscale": [[0.0, "#0d0887"], [0.1111111111111111, "#46039f"], [0.2222222222222222, "#7201a8"], [0.3333333333333333, "#9c179e"], [0.4444444444444444, "#bd3786"], [0.5555555555555556, "#d8576b"], [0.6666666666666666, "#ed7953"], [0.7777777777777778, "#fb9f3a"], [0.8888888888888888, "#fdca26"], [1.0, "#f0f921"]]}], "mesh3d": [{"type": "mesh3d", "colorbar": {"outlinewidth": 0, "ticks": ""}}], "scatter": [{"fillpattern": {"fillmode": "overlay", "size": 10, "solidity": 0.2}, "type": "scatter"}], "parcoords": [{"type": "parcoords", "line": {"colorbar": {"outlinewidth": 0, "ticks": ""}}}], "scatterpolargl": [{"type": "scatterpolargl", "marker": {"colorbar": {"outlinewidth": 0, "ticks": ""}}}], "bar": [{"error_x": {"color": "#2a3f5f"}, "error_y": {"color": "#2a3f5f"}, "marker": {"line": {"color": "#E5ECF6", "width": 0.5}, "pattern": {"fillmode": "overlay", "size": 10, "solidity": 0.2}}, "type": "bar"}], "scattergeo": [{"type": "scattergeo", "marker": {"colorbar": {"outlinewidth": 0, "ticks": ""}}}], "scatterpolar": [{"type": "scatterpolar", "marker": {"colorbar": {"outlinewidth": 0, "ticks": ""}}}], "histogram": [{"marker": {"pattern": {"fillmode": "overlay", "size": 10, "solidity": 0.2}}, "type": "histogram"}], "scattergl": [{"type": "scattergl", "marker": {"colorbar": {"outlinewidth": 0, "ticks": ""}}}], "scatter3d": [{"type": "scatter3d", "line": {"colorbar": {"outlinewidth": 0, "ticks": ""}}, "marker": {"colorbar": {"outlinewidth": 0, "ticks": ""}}}], "scattermapbox": [{"type": "scattermapbox", "marker": {"colorbar": {"outlinewidth": 0, "ticks": ""}}}], "scatterternary": [{"type": "scatterternary", "marker": {"colorbar": {"outlinewidth": 0, "ticks": ""}}}], "scattercarpet": [{"type": "scattercarpet", "marker": {"colorbar": {"outlinewidth": 0, "ticks": ""}}}], "carpet": [{"aaxis": {"endlinecolor": "#2a3f5f", "gridcolor": "white", "linecolor": "white", "minorgridcolor": "white", "startlinecolor": "#2a3f5f"}, "baxis": {"endlinecolor": "#2a3f5f", "gridcolor": "white", "linecolor": "white", "minorgridcolor": "white", "startlinecolor": "#2a3f5f"}, "type": "carpet"}], "table": [{"cells": {"fill": {"color": "#EBF0F8"}, "line": {"color": "white"}}, "header": {"fill": {"color": "#C8D4E3"}, "line": {"color": "white"}}, "type": "table"}], "barpolar": [{"marker": {"line": {"color": "#E5ECF6", "width": 0.5}, "pattern": {"fillmode": "overlay", "size": 10, "solidity": 0.2}}, "type": "barpolar"}], "pie": [{"automargin": true, "type": "pie"}]}, "layout": {"autotypenumbers": "strict", "colorway": ["#636efa", "#EF553B", "#00cc96", "#ab63fa", "#FFA15A", "#19d3f3", "#FF6692", "#B6E880", "#FF97FF", "#FECB52"], "font": {"color": "#2a3f5f"}, "hovermode": "closest", "hoverlabel": {"align": "left"}, "paper_bgcolor": "white", "plot_bgcolor": "#E5ECF6", "polar": {"bgcolor": "#E5ECF6", "angularaxis": {"gridcolor": "white", "linecolor": "white", "ticks": ""}, "radialaxis": {"gridcolor": "white", "linecolor": "white", "ticks": ""}}, "ternary": {"bgcolor": "#E5ECF6", "aaxis": {"gridcolor": "white", "linecolor": "white", "ticks": ""}, "baxis": {"gridcolor": "white", "linecolor": "white", "ticks": ""}, "caxis": {"gridcolor": "white", "linecolor": "white", "ticks": ""}}, "coloraxis": {"colorbar": {"outlinewidth": 0, "ticks": ""}}, "colorscale": {"sequential": [[0.0, "#0d0887"], [0.1111111111111111, "#46039f"], [0.2222222222222222, "#7201a8"], [0.3333333333333333, "#9c179e"], [0.4444444444444444, "#bd3786"], [0.5555555555555556, "#d8576b"], [0.6666666666666666, "#ed7953"], [0.7777777777777778, "#fb9f3a"], [0.8888888888888888, "#fdca26"], [1.0, "#f0f921"]], "sequentialminus": [[0.0, "#0d0887"], [0.1111111111111111, "#46039f"], [0.2222222222222222, "#7201a8"], [0.3333333333333333, "#9c179e"], [0.4444444444444444, "#bd3786"], [0.5555555555555556, "#d8576b"], [0.6666666666666666, "#ed7953"], [0.7777777777777778, "#fb9f3a"], [0.8888888888888888, "#fdca26"], [1.0, "#f0f921"]], "diverging": [[0, "#8e0152"], [0.1, "#c51b7d"], [0.2, "#de77ae"], [0.3, "#f1b6da"], [0.4, "#fde0ef"], [0.5, "#f7f7f7"], [0.6, "#e6f5d0"], [0.7, "#b8e186"], [0.8, "#7fbc41"], [0.9, "#4d9221"], [1, "#276419"]]}, "xaxis": {"gridcolor": "white", "linecolor": "white", "ticks": "", "title": {"standoff": 15}, "zerolinecolor": "white", "automargin": true, "zerolinewidth": 2}, "yaxis": {"gridcolor": "white", "linecolor": "white", "ticks": "", "title": {"standoff": 15}, "zerolinecolor": "white", "automargin": true, "zerolinewidth": 2}, "scene": {"xaxis": {"backgroundcolor": "#E5ECF6", "gridcolor": "white", "linecolor": "white", "showbackground": true, "ticks": "", "zerolinecolor": "white", "gridwidth": 2}, "yaxis": {"backgroundcolor": "#E5ECF6", "gridcolor": "white", "linecolor": "white", "showbackground": true, "ticks": "", "zerolinecolor": "white", "gridwidth": 2}, "zaxis": {"backgroundcolor": "#E5ECF6", "gridcolor": "white", "linecolor": "white", "showbackground": true, "ticks": "", "zerolinecolor": "white", "gridwidth": 2}}, "shapedefaults": {"line": {"color": "#2a3f5f"}}, "annotationdefaults": {"arrowcolor": "#2a3f5f", "arrowhead": 0, "arrowwidth": 1}, "geo": {"bgcolor": "white", "landcolor": "#E5ECF6", "subunitcolor": "white", "showland": true, "showlakes": true, "lakecolor": "white"}, "title": {"x": 0.05}, "mapbox": {"style": "light"}}}, "title": {"text": "Rating"}, "xaxis": {"title": {"text": "Iteration"}}, "yaxis": {"title": {"text": "TrueSkill"}}}}